[[{"id":0,"latitude":582,"longitude":770},{"id":6,"task":3,"type":"pickup","latitude":595,"longitude":944,"relatedTaskId":null},{"id":30,"task":15,"type":"pickup","latitude":291,"longitude":895,"relatedTaskId":null},{"id":31,"task":15,"type":"drop","latitude":369,"longitude":619,"relatedTaskId":null},{"id":42,"task":21,"type":"pickup","latitude":579,"longitude":1272,"relatedTaskId":null},{"id":7,"task":3,"type":"drop","latitude":528,"longitude":1645,"relatedTaskId":null},{"id":43,"task":21,"type":"drop","latitude":81,"longitude":1689,"relatedTaskId":null}],[{"id":1,"latitude":494,"longitude":472},{"id":44,"task":22,"type":"pickup","latitude":534,"longitude":589,"relatedTaskId":null},{"id":18,"task":9,"type":"pickup","latitude":671,"longitude":336,"relatedTaskId":null},{"id":19,"task":9,"type":"drop","latitude":593,"longitude":154,"relatedTaskId":null},{"id":45,"task":22,"type":"drop","latitude":482,"longitude":47,"relatedTaskId":null},{"id":28,"task":14,"type":"pickup","latitude":112,"longitude":1512,"relatedTaskId":null},{"id":29,"task":14,"type":"drop","latitude":828,"longitude":647,"relatedTaskId":null}],[{"id":2,"latitude":751,"longitude":37},{"id":54,"task":27,"type":"pickup","latitude":860,"longitude":115,"relatedTaskId":null},{"id":55,"task":27,"type":"drop","latitude":857,"longitude":212,"relatedTaskId":null},{"id":36,"task":18,"type":"pickup","latitude":900,"longitude":741,"relatedTaskId":null},{"id":37,"task":18,"type":"drop","latitude":444,"longitude":262,"relatedTaskId":null},{"id":56,"task":28,"type":"pickup","latitude":72,"longitude":1521,"relatedTaskId":null},{"id":57,"task":28,"type":"drop","latitude":769,"longitude":40,"relatedTaskId":null}],[{"id":3,"latitude":12,"longitude":863},{"id":26,"task":13,"type":"pickup","latitude":143,"longitude":929,"relatedTaskId":null},{"id":16,"task":8,"type":"pickup","latitude":145,"longitude":678,"relatedTaskId":null},{"id":58,"task":29,"type":"pickup","latitude":1,"longitude":490,"relatedTaskId":null},{"id":0,"task":0,"type":"pickup","latitude":202,"longitude":1432,"relatedTaskId":null},{"id":59,"task":29,"type":"drop","latitude":200,"longitude":1455,"relatedTaskId":null},{"id":1,"task":0,"type":"drop","latitude":655,"longitude":1070,"relatedTaskId":null},{"id":27,"task":13,"type":"drop","latitude":751,"longitude":797,"relatedTaskId":null},{"id":17,"task":8,"type":"drop","latitude":507,"longitude":189,"relatedTaskId":null}],[{"id":4,"latitude":736,"longitude":468},{"id":4,"task":2,"type":"pickup","latitude":733,"longitude":336,"relatedTaskId":null},{"id":32,"task":16,"type":"pickup","latitude":876,"longitude":599,"relatedTaskId":null},{"id":34,"task":17,"type":"pickup","latitude":713,"longitude":1241,"relatedTaskId":null},{"id":35,"task":17,"type":"drop","latitude":881,"longitude":708,"relatedTaskId":null},{"id":5,"task":2,"type":"drop","latitude":9,"longitude":1012,"relatedTaskId":null},{"id":33,"task":16,"type":"drop","latitude":245,"longitude":1784,"relatedTaskId":null}],[{"id":5,"latitude":851,"longitude":1040},{"id":52,"task":26,"type":"pickup","latitude":815,"longitude":1056,"relatedTaskId":null},{"id":20,"task":10,"type":"pickup","latitude":873,"longitude":1101,"relatedTaskId":null},{"id":21,"task":10,"type":"drop","latitude":734,"longitude":1200,"relatedTaskId":null},{"id":12,"task":6,"type":"pickup","latitude":479,"longitude":1310,"relatedTaskId":null},{"id":13,"task":6,"type":"drop","latitude":160,"longitude":121,"relatedTaskId":null},{"id":53,"task":26,"type":"drop","latitude":42,"longitude":0,"relatedTaskId":null}],[{"id":6,"latitude":733,"longitude":1783},{"id":22,"task":11,"type":"pickup","latitude":495,"longitude":1793,"relatedTaskId":null},{"id":23,"task":11,"type":"drop","latitude":450,"longitude":1693,"relatedTaskId":null},{"id":40,"task":20,"type":"pickup","latitude":861,"longitude":1488,"relatedTaskId":null},{"id":8,"task":4,"type":"pickup","latitude":300,"longitude":1646,"relatedTaskId":null},{"id":9,"task":4,"type":"drop","latitude":820,"longitude":1446,"relatedTaskId":null},{"id":41,"task":20,"type":"drop","latitude":298,"longitude":1034,"relatedTaskId":null}],[{"id":7,"latitude":281,"longitude":270},{"id":46,"task":23,"type":"pickup","latitude":473,"longitude":56,"relatedTaskId":null},{"id":2,"task":1,"type":"pickup","latitude":518,"longitude":105,"relatedTaskId":null},{"id":3,"task":1,"type":"drop","latitude":193,"longitude":276,"relatedTaskId":null},{"id":38,"task":19,"type":"pickup","latitude":283,"longitude":1517,"relatedTaskId":null},{"id":39,"task":19,"type":"drop","latitude":259,"longitude":615,"relatedTaskId":null},{"id":47,"task":23,"type":"drop","latitude":122,"longitude":1680,"relatedTaskId":null}],[{"id":8,"latitude":490,"longitude":997},{"id":50,"task":25,"type":"pickup","latitude":642,"longitude":1022,"relatedTaskId":null},{"id":48,"task":24,"type":"pickup","latitude":593,"longitude":1195,"relatedTaskId":null},{"id":10,"task":5,"type":"pickup","latitude":496,"longitude":1262,"relatedTaskId":null},{"id":11,"task":5,"type":"drop","latitude":407,"longitude":581,"relatedTaskId":null},{"id":49,"task":24,"type":"drop","latitude":773,"longitude":453,"relatedTaskId":null},{"id":51,"task":25,"type":"drop","latitude":155,"longitude":137,"relatedTaskId":null}],[{"id":9,"latitude":525,"longitude":524},{"id":24,"task":12,"type":"pickup","latitude":637,"longitude":329,"relatedTaskId":null},{"id":14,"task":7,"type":"pickup","latitude":897,"longitude":609,"relatedTaskId":null},{"id":15,"task":7,"type":"drop","latitude":503,"longitude":234,"relatedTaskId":null},{"id":25,"task":12,"type":"drop","latitude":615,"longitude":902,"relatedTaskId":null}]]